{ 
  "emy.ego.fluffy_slime_100" : [ 
    {
      "name" : "Vibrator",
      "icon" : "https://raw.githubusercontent.com/EgoLLC/EgoLLC.github.io/master/ic_vibrator.png",
      "package" : "ego.emy.vibrator"
    },
    {
      "name" : "BoxMaker",
      "icon" : "https://raw.githubusercontent.com/EgoLLC/EgoLLC.github.io/master/ic_boxmaker.png",
      "package" : "ego.emy.boxmaker"
    },
    {
      "name" : "Fertilization",
      "icon" : "https://raw.githubusercontent.com/EgoLLC/EgoLLC.github.io/master/ic_fertilization.png",
      "package" : "ego.emy.fertilization"
    }
  ],
  "ego.emy.boxmaker" : [ 
    {
      "name" : "Vibrator",
      "icon" : "https://raw.githubusercontent.com/EgoLLC/EgoLLC.github.io/master/ic_vibrator.png",
      "package" : "ego.emy.vibrator"
    },
    {
      "name" : "Fluffy Slime 100",
      "icon" : "https://raw.githubusercontent.com/EgoLLC/EgoLLC.github.io/master/ic_boxmaker.png",
      "package" : "emy.ego.fluffy_slime_100"
    },
    {
      "name" : "Fertilization",
      "icon" : "https://raw.githubusercontent.com/EgoLLC/EgoLLC.github.io/master/ic_fertilization.png",
      "package" : "ego.emy.fertilization"
    }
  ],
    "ego.art.coloring" : [ 
    {
      "name" : "Vibrator",
      "icon" : "https://raw.githubusercontent.com/EgoLLC/EgoLLC.github.io/master/ic_vibrator.png",
      "package" : "ego.emy.vibrator"
    },
    {
      "name" : "Box Maker",
      "icon" : "https://raw.githubusercontent.com/EgoLLC/EgoLLC.github.io/master/ic_boxmaker.png",
      "package" : "ego.emy.boxmaker"
    },
    {
      "name" : "Fertilization",
      "icon" : "https://www.google.com/imgres?imgurl=https%3A%2F%2Fai.phncdn.com%2Fvideos%2F201705%2F28%2F118204501%2Foriginal%2F(m%3DeafTGgaaaa)(mh%3DtsbV7HadGuvnoIoY)14.jpg&imgrefurl=https%3A%2F%2Fwww.thumbzilla.com%2Fvideo%2Fph592afea41bdfa%2Fvinam-the-best-girl-pusy&tbnid=b9cCOWNcIjMtgM&vet=12ahUKEwiZs-Psvq_rAhXEsioKHda0DqwQMygUegUIARCpAQ..i&docid=hekcmDQaeVHVOM&w=320&h=180&q=pusy&ved=2ahUKEwiZs-Psvq_rAhXEsioKHda0DqwQMygUegUIARCpAQ",
      "package" : "ego.emy.fertilization"
    }
  ]
}
